nirum/__init__.py
nirum/_compat.py
nirum/constructs.py
nirum/datastructures.py
nirum/exc.py
nirum/func.py
nirum/service.py
nirum/test.py
nirum/transport.py
nirum-0.7.0.dist-info/LICENSE
nirum-0.7.0.dist-info/METADATA
nirum-0.7.0.dist-info/WHEEL
nirum-0.7.0.dist-info/top_level.txt
nirum-0.7.0.dist-info/RECORD
