Metadata-Version: 2.1
Name: nirum
Version: 0.7.0
Summary: The Nirum runtime library for Python
Home-page: https://github.com/nirum-lang/nirum-python
Author: Kang Hyojun
Author-email: iam.kanghyojun@gmail.com
License: MIT license
Platform: UNKNOWN
Classifier: Development Status :: 4 - Beta
Classifier: Intended Audience :: Developers
Classifier: License :: OSI Approved :: MIT License
Classifier: Operating System :: OS Independent
Classifier: Programming Language :: Python :: 2.7
Classifier: Programming Language :: Python :: 3.4
Classifier: Programming Language :: Python :: 3.5
Classifier: Programming Language :: Python :: 3.6
Classifier: Topic :: Internet :: WWW/HTTP :: WSGI :: Application
Classifier: Topic :: Software Development :: Code Generators
Classifier: Topic :: Software Development :: Libraries :: Python Modules
Classifier: Topic :: Software Development :: Object Brokering
Requires-Dist: six
Requires-Dist: iso8601
Requires-Dist: enum34 ; python_version<'3.4'
Requires-Dist: typing ; python_version<'3.5'
Provides-Extra: docs
Requires-Dist: Sphinx ; extra == 'docs'
Provides-Extra: tests
Requires-Dist: pycodestyle (<2.4.0,>=2.0) ; extra == 'tests'
Requires-Dist: pytest (<4.0.0,>=3.2.3) ; extra == 'tests'
Requires-Dist: pytest-flake8 (<1.0.0,>=0.9.1) ; extra == 'tests'
Requires-Dist: flake8-import-order (<1.0,>=0.12) ; extra == 'tests'
Requires-Dist: flake8-import-order-spoqa (<2.0.0,>=1.0.1) ; extra == 'tests'
